<?xml version="1.0" encoding="utf-8"?>
<issues>
  <issue>
    <field name="Priority">
      <value>Critical</value>
    </field>
    <field name="Type">
      <value>Feature</value>
    </field>
    <field name="State">
      <value>Won't fix</value>
    </field>
    <field name="Assignee" />
    <field name="Subsystem">
      <value>.NET 2.0 Support</value>
    </field>
    <field name="Fix versions" />
    <field name="Affected versions" />
    <field name="Fixed in build" />
    <field name="numberInProject">
      <value>72</value>
    </field>
    <field name="summary">
      <value>Uploading and saving a file in the SQL database using ACTIVE RECORD</value>
    </field>
    <field name="description">
      <value>I need to know of a way to upload and save a textfile using Active Record.Please give examples too.
I need to upload a file from the file directory(e.g C:\Files) and store it in the database.
I am using the sql server database.
Are there any tools I can use or is using Active record be able to help me?</value>
    </field>
    <field name="created">
      <value>1155601016000</value>
    </field>
    <field name="updated">
      <value>1155603818000</value>
    </field>
    <field name="reporterName">
      <value>mphiri</value>
    </field>
    <field name="updaterName">
      <value>mphiri</value>
    </field>
    <field name="resolved">
      <value>1282136175948</value>
    </field>
    <field name="permittedGroup">
      <value>All Users</value>
    </field>
  </issue>
</issues>