<?xml version="1.0" encoding="utf-8"?>
<issues>
  <issue>
    <field name="Priority">
      <value>Minor</value>
    </field>
    <field name="Type">
      <value>Feature</value>
    </field>
    <field name="State">
      <value>Obsolete</value>
    </field>
    <field name="Assignee" />
    <field name="Subsystem">
      <value>No subsystem</value>
    </field>
    <field name="Fix versions" />
    <field name="Affected versions" />
    <field name="Fixed in build" />
    <field name="numberInProject">
      <value>154</value>
    </field>
    <field name="summary">
      <value>Parameter binders to play with MonoRail and Google Protocol Buffers</value>
    </field>
    <field name="description">
      <value>Here is IParameterBinder for deserializing and ProtoResponseReturnBinderAttribute for serializing MonoRail controller's action I/O that use Google's Protocol Buffers messages.

Theses are currently usable if relying on MicroKernel and protobuf csharp port lib.

One idea might be to integrate this as a Rest contrib project

another one is to build a protobuf facility (by APIizing current dependency to google protobuf lib to a backend).

If you are in hurry, it also has it goodness on it own</value>
    </field>
    <field name="created">
      <value>1245461310000</value>
    </field>
    <field name="updated">
      <value>1414392322876</value>
    </field>
    <field name="reporterName">
      <value>gauthier</value>
    </field>
    <field name="updaterName">
      <value>jonorossi</value>
    </field>
    <field name="resolved">
      <value>1414392322869</value>
    </field>
    <field name="permittedGroup">
      <value>All Users</value>
    </field>
    <comment author="gauthier" text="see http://groups.google.com/group/castle-project-devel/browse_frm/thread/b532d4772df31c65 for actual code sample" created="1245461647000" />
    <comment author="gauthier" text="* '''Attachment''' ProtoParamBindAttribute.cs added.&#xD;&#xA;" created="1245461580000" />
    <comment author="gauthier" text="* '''Attachment''' ProtoResponseReturnBinderAttribute.cs added.&#xD;&#xA;" created="1245461580000" />
  </issue>
</issues>