<?xml version="1.0" encoding="utf-8"?>
<issues>
  <issue>
    <field name="Priority">
      <value>Major</value>
    </field>
    <field name="Type">
      <value>Feature</value>
    </field>
    <field name="State">
      <value>Incomplete</value>
    </field>
    <field name="Assignee" />
    <field name="Subsystem">
      <value>Core</value>
    </field>
    <field name="Fix versions" />
    <field name="Affected versions">
      <value>2.0 Beta 1</value>
    </field>
    <field name="Fixed in build" />
    <field name="numberInProject">
      <value>45</value>
    </field>
    <field name="summary">
      <value>Support for Interception of Equals / GetHashCode/ ToString Methods</value>
    </field>
    <field name="description">
      <value>It would be nice if we had support for Interception of Equals / GetHashCode/ ToString Methods. 
This would make it easier to implement custom Equals/GetHashCode/ToString for the Proxy.
</value>
    </field>
    <field name="created">
      <value>1167827376000</value>
    </field>
    <field name="updated">
      <value>1173608628000</value>
    </field>
    <field name="reporterName">
      <value>thomas.darimont</value>
    </field>
    <field name="updaterName">
      <value>thomas.darimont</value>
    </field>
    <field name="resolved">
      <value>1282140668088</value>
    </field>
    <field name="permittedGroup">
      <value>All Users</value>
    </field>
  </issue>
</issues>